Workbook

Sheet Fondos
A1: ID | B1: Fondo | C1: Administradora | D1: Horizonte | E1: Fecha Inicio
A2: BBVACASH | B2: BBVA CASH SOLES BBVA SAF | C2: BBVA SAF | D2: MCP | E2: 39784
A3: BBVARENTACORTOPLAZO | B3: BBVA RENTA CORTO PLAZO S/. BBVA SAF | C3: BBVA SAF | D3: CP | E3: 38713
A4: BBVATESORERIASOLES | B4: BBVA TESORERIA SOLES FMIV BBVA SAF | C4: BBVA SAF | D4: CP | E4: 43376
A5: CREDCONSERCORTOPLAZO | B5: CRED. CONSER. CORTO PLAZO S/ CREDICORP SAF | C5: CREDICORP SAF | D5: CP | E5: 41680
A6: CREDCONSERVADLIQUIDEZ | B6: CRED. CONSERVAD. LIQUIDEZ S/ CREDICORP SAF | C6: CREDICORP SAF | D6: MCP | E6: 36622
A7: SFLiquidez | B7: SF Liquidez S/. SCOTIA FONDOS | C7: SCOTIA FONDOS | D7: MCP | E7: 44956
A8: SURACORTOPLAZOSOLES | B8: SURA CORTO PLAZO SOLES FONDOS SURA SAF | C8: FONDOS SURA SAF | D8: CP | E8: 39897
A9: SURAULTRACASHSOLES | B9: SURA ULTRA CASH SOLES FONDOS SURA SAF | C9: FONDOS SURA SAF | D9: MCP | E9: 41038
A10: BBVARENTAMEDPLAZO | B10: BBVA RENTA MED. PLAZO S/. BBVA SAF | C10: BBVA SAF | D10: MP | E10: 35720
A11: CCMEDPLAZO | B11: CC CONSERV. MED. PLAZO S/. CREDICORP SAF | C11: CREDICORP SAF | D11: MP | E11: 39150
A12: IFMEDIANOPLAZO | B12: IF MEDIANO PLAZO SOLES INTERFONDO | C12: INTERFONDO | D12: MP | E12: 37329
A13: SURARENTASOLES | B13: SURA RENTA SOLES FONDOS SURA SAF | C13: FONDOS SURA SAF | D13: MP | E13: 38856
A14: ETFPESOV | B14: ETFPESOV | C14: EL DORADO | D14: ETF | E14: 45747

Sheet Data
A1: Fecha | B1: ID | C1: Valor Cuota | D1: Patrimonio | E1: Partícipes
A2: 44926 | B2: BBVACASH | C2: 144.59972 | D2: 1.7805957e+09 | E2: 71633
A3: 44926 | B3: BBVARENTACORTOPLAZO | C3: 173.7172 | D3: 2.3560769e+08 | E3: 6188
A4: 44926 | B4: BBVATESORERIASOLES | C4: 111.44878 | D4: 1.648744e+08 | E4: 191
A5: 44926 | B5: CREDCONSERCORTOPLAZO | C5: 135.21021 | D5: 4.7676765e+08 | E5: 10418
A6: 44926 | B6: CREDCONSERVADLIQUIDEZ | C6: 296.69449 | D6: 1.4978066e+09 | E6: 28520
A7: 44926 | B7: SFLiquidez
A8: 44926 | B8: SURACORTOPLAZOSOLES | C8: 167.82192 | D8: 1.8142023e+08 | E8: 827
A9: 44926 | B9: SURAULTRACASHSOLES | C9: 144.00388 | D9: 5.731377e+08 | E9: 1948
A10: 44926 | B10: BBVARENTAMEDPLAZO | C10: 317.51362 | D10: 75204729 | E10: 4096
A11: 44926 | B11: CCMEDPLAZO | C11: 177.00757 | D11: 3.2910728e+08 | E11: 5181
A12: 44926 | B12: IFMEDIANOPLAZO | C12: 186.8327 | D12: 52576790 | E12: 3251
A13: 44926 | B13: SURARENTASOLES | C13: 195.25891 | D13: 47421040 | E13: 620
A14: 45291 | B14: BBVACASH | C14: 155.05097 | D14: 1.7577186e+09 | E14: 67700
A15: 45291 | B15: BBVARENTACORTOPLAZO | C15: 187.24948 | D15: 2.2387548e+08 | E15: 4845
A16: 45291 | B16: BBVATESORERIASOLES | C16: 119.44997 | D16: 87141003 | E16: 178
A17: 45291 | B17: CREDCONSERCORTOPLAZO | C17: 145.55335 | D17: 4.772457e+08 | E17: 10554
A18: 45291 | B18: CREDCONSERVADLIQUIDEZ | C18: 318.38267 | D18: 1.640067e+09 | E18: 30709
A19: 45291 | B19: SFLiquidez | C19: 10.796559 | D19: 7.2271873e+08 | E19: 6888
... A198: 46142 | B198: CREDCONSERVADLIQUIDEZ | C198: 355.20416 | D198: 3.0877245e+09 | E198: 42706
A199: 46142 | B199: SFLiquidez | C199: 11.991466 | D199: 1.2740405e+09 | E199: 16547 | I199: 1.98 | J199: 3.17 | K199: 3.47 | L199: 4.1 | M199: 3.64 | N199: 3.76 | O199: 3.95 | P199: 4.31 | Q199: 4.53 | R199: 4.38
A200: 46142 | B200: SURACORTOPLAZOSOLES | C200: 200.90347 | D200: 2.7268767e+08 | E200: 928 | I200: - | J200: 0.82 | K200: 2.11 | L200: 3.5 | M200: 4.33 | N200: 3.12 | O200: 4.43 | P200: 4.1 | Q200: - | R200: 4.92
A201: 46142 | B201: SURAULTRACASHSOLES | C201: 173.04719 | D201: 1.4398076e+09 | E201: 2039 | I201: 2.97 | J201: 3.14 | K201: 3.16 | L201: 2.84 | M201: 2.71 | N201: 3.92 | O201: 4.08 | P201: 4.34 | Q201: 4.48 | R201: 4.4
A202: 46142 | B202: BBVARENTAMEDPLAZO | C202: 406.12916 | D202: 4.7119646e+08 | E202: 8591 | I202: - | J202: 3.73 | K202: 4.15 | L202: 4.11 | M202: 4.6 | N202: 2.96 | O202: 3.47 | P202: - | Q202: 3.52 | R202: 3.85
A203: 46142 | B203: CCMEDPLAZO | C203: 223.68921 | D203: 8.0865092e+08 | E203: 7994 | I203: 2.94 | J203: 3.93 | K203: 4.23 | L203: 4.37 | M203: 3.96 | N203: 4.07 | O203: 4.2 | P203: 4.22 | Q203: 3.88 | R203: 3.37
A204: 46142 | B204: IFMEDIANOPLAZO | C204: 233.0134 | D204: 1.0790431e+08 | E204: 4544 | I204: 1.58 | J204: 2.99 | K204: 3.1 | L204: 3.44 | M204: 4.06 | N204: 3.73 | O204: 3.9 | P204: 4.1 | Q204: 3 | R204: 4.54
A205: 46142 | B205: SURARENTASOLES | C205: 240.5918 | D205: 1.2793668e+08 | E205: 910 | I205: - | J205: - | K205: - | L205: - | M205: - | N205: 2.92 | O205: 2.83 | P205: - | Q205: - | R205: -
A206: 46142 | B206: ETFPESOV | C206: 109.30136 | D206: 1.9400992e+08 | E206: 446 | I206: - | J206: 3.88 | K206: 3.79 | L206: 3.88 | M206: 4.34 | N206: 3.85 | O206: 4.13 | P206: 4.34 | Q206: 4.5 | R206: 4.48
A207: 46173 | B207: BBVACASH | C207: 173.16881 | D207: 2.7720311e+09 | E207: 76924 | I207: 2.12 | J207: 2.68 | K207: 2.67 | L207: 3.15 | M207: 4.87 | N207: 4.05 | O207: 4.24 | P207: 4.14 | Q207: 4.12 | R207: 4.63
A208: 46173 | B208: BBVARENTACORTOPLAZO | C208: 211.85907 | D208: 8.9365279e+08 | E208: 7233 | I208: - | J208: 4.64 | K208: 5.07 | L208: 4.69 | M208: 4.18 | N208: 3.99 | O208: 4.13 | P208: 4.43 | Q208: 4.47 | R208: 4.01
A209: 46173 | B209: BBVATESORERIASOLES | C209: 133.89353 | D209: 2.8069718e+08 | E209: 546 | I209: 0.1 | J209: 0.87 | K209: 3.04 | L209: 3.43 | M209: 3.61 | N209: 4.15 | O209: 4.48 | P209: - | Q209: 4.33 | R209: 4.33
A210: 46173 | B210: CREDCONSERCORTOPLAZO | C210: 164.40488 | D210: 1.2955914e+09 | E210: 13608 | I210: 4.07 | J210: 4.47 | K210: 4.31 | L210: 4.4 | M210: - | N210: 3.87 | O210: 4.22 | P210: 4.33 | Q210: 4.62 | R210: 4.48
A211: 46173 | B211: CREDCONSERVADLIQUIDEZ | C211: 356.45456 | D211: 3.1117907e+09 | E211: 43571 | I211: - | J211: - | K211: 3.08 | L211: 4 | M211: 3.98 | N211: - | O211: - | P211: - | Q211: - | R211: -
A212: 46173 | B212: SFLiquidez | C212: 12.034792 | D212: 1.2187905e+09 | E212: 16642 | I212: 2.31 | J212: 2.85 | K212: 2.16 | L212: 3.97 | M212: 4.6 | N212: - | O212: - | P212: - | Q212: - | R212: 5.18
A213: 46173 | B213: SURACORTOPLAZOSOLES | C213: 201.68211 | D213: 2.7119357e+08 | E213: 917 | I213: - | J213: - | K213: - | L213: - | M213: - | N213: 4.03 | O213: 4.34 | P213: 4.4 | Q213: - | R213: -
A214: 46173 | B214: SURAULTRACASHSOLES | C214: 173.65543 | D214: 1.4835407e+09 | E214: 2017 | I214: - | J214: - | K214: - | L214: - | M214: - | N214: 3.6 | O214: 4.2 | P214: 4.3 | Q214: - | R214: -
A215: 46173 | B215: BBVARENTAMEDPLAZO | C215: 407.7372 | D215: 4.6039415e+08 | E215: 8504 | I215: - | J215: - | K215: - | L215: - | M215: - | N215: 3.94 | O215: 4.44 | P215: 4.44 | Q215: 4.78 | R215: 4.92
A216: 46173 | B216: CCMEDPLAZO | C216: 225.18914 | D216: 821868199 | E216: 8009 | I216: 0.5 | J216: 0.68 | K216: 4.89 | L216: 4.67 | M216: 4.66 | N216: 2.26 | O216: 4.14 | P216: 0.5 | Q216: 3.99 | R216: 4.61
A217: 46173 | B217: IFMEDIANOPLAZO | C217: 233.8266 | D217: 1.0626809e+08 | E217: 4494 | I217: 0.8 | J217: 3.45 | K217: 3.65 | L217: 3.74 | M217: 3.26 | N217: 4.3 | O217: 4.43 | P217: 4.46 | Q217: 4.63 | R217: 2.8
A218: 46173 | B218: SURARENTASOLES | C218: 241.93932 | D218: 1.2660435e+08 | E218: 900 | I218: - | J218: 4.5 | K218: 4.76 | L218: 5.07 | M218: 5.58 | N218: - | O218: - | P218: - | Q218: - | R218: 3.75
A219: 46173 | B219: ETFPESOV | C219: 110.21059 | D219: 1.9810354e+08 | E219: 449 | I219: 3.45 | J219: 3.53 | K219: 3.32 | L219: 3.63 | M219: 3.92 | N219: 3.88 | O219: 4.12 | P219: 4.27 | Q219: 4.18 | R219: 4.52
A220: 46203 | B220: BBVACASH | C220: 173.72935 | D220: 2.7550294e+09 | E220: 76508
A221: 46203 | B221: BBVARENTACORTOPLAZO | C221: 212.78309 | D221: 9.1372989e+08 | E221: 7226
A222: 46203 | B222: BBVATESORERIASOLES | C222: 134.35108 | D222: 2.9407014e+08 | E222: 559
A223: 46203 | B223: CREDCONSERCORTOPLAZO | C223: 165.16175 | D223: 1.2739863e+09 | E223: 13634
A224: 46203 | B224: CREDCONSERVADLIQUIDEZ | C224: 357.63222 | D224: 3.1554283e+09 | E224: 44078
A225: 46203 | B225: SFLiquidez | C225: 12.079792 | D225: 1.2394127e+09 | E225: 16616
A226: 46203 | B226: SURACORTOPLAZOSOLES | C226: 202.47938 | D226: 2.6898149e+08 | E226: 909
A227: 46203 | B227: SURAULTRACASHSOLES | C227: 174.30474 | D227: 1.4155239e+09 | E227: 2017
A228: 46203 | B228: BBVARENTAMEDPLAZO | C228: 410.65932 | D228: 4.6114313e+08 | E228: 8438
A229: 46203 | B229: CCMEDPLAZO | C229: 227.20659 | D229: 8.4142897e+08 | E229: 8102
A230: 46203 | B230: IFMEDIANOPLAZO | C230: 235.3936 | D230: 1.0497997e+08 | E230: 4508
A231: 46203 | B231: SURARENTASOLES | C231: 243.78792 | D231: 1.2723361e+08 | E231: 888
... A297: 46311 | B297: ETFPESOV | C297: 110.9762 | D297: 1.4957643e+08 | E297: 547

Sheet Hoja1
B1: Mi Base | C1: Base SMV | D1: Valor Cuota | E1: Patrimonio | F1: Partícipes
B2: BBVACASH | C2: BBVA CASH SOLES BBVA SAF | D2: =VLOOKUP(C2,Hoja2!B:Q,5,0) -> 175.83459 | E2: =VLOOKUP(C2,Hoja2!B:Q,12,0) -> 2.7054502e+09 | F2: =VLOOKUP(C2,Hoja2!B:Q,14,0) -> 75059
B3: BBVARENTACORTOPLAZO | C3: BBVA RENTA CORTO PLAZO S/. BBVA SAF | D3: =VLOOKUP(C3,Hoja2!B:Q,5,0) -> 215.18729 | E3: =VLOOKUP(C3,Hoja2!B:Q,12,0) -> 9.0160384e+08 | F3: =VLOOKUP(C3,Hoja2!B:Q,14,0) -> 7051
B4: BBVATESORERIASOLES | C4: BBVA TESORERIA SOLES FMIV BBVA SAF | D4: =VLOOKUP(C4,Hoja2!B:Q,5,0) -> 136.05661 | E4: =VLOOKUP(C4,Hoja2!B:Q,12,0) -> 3.9166551e+08 | F4: =VLOOKUP(C4,Hoja2!B:Q,14,0) -> 614
B5: CREDCONSERCORTOPLAZO | C5: CRED. CONSER. CORTO PLAZO S/ CREDICORP SAF | D5: =VLOOKUP("CREDICORP SAF-CRED. CONSER. CORTO PLAZO S/ SERIE A",Hoja2!B:Q,5,0) -> 166.77473 | E5: =VLOOKUP(C5,Hoja2!B:Q,12,0) -> 1.3128841e+09 | F5: =VLOOKUP(C5,Hoja2!B:Q,14,0) -> 13772
B6: CREDCONSERVADLIQUIDEZ | C6: CRED. CONSERVAD. LIQUIDEZ S/ CREDICORP SAF | D6: =VLOOKUP("CREDICORP SAF-CRED. CONSERVAD. LIQUIDEZ S/ SERIE A",Hoja2!B:Q,5,0) -> 361.75433 | E6: =VLOOKUP(C6,Hoja2!B:Q,12,0) -> 3.4812322e+09 | F6: =VLOOKUP(C6,Hoja2!B:Q,14,0) -> 45788
B7: SFLiquidez | C7: SF Liquidez S/. SCOTIA FONDOS | D7: =VLOOKUP(C7,Hoja2!B:Q,5,0) -> 12.225661 | E7: =VLOOKUP(C7,Hoja2!B:Q,12,0) -> 1.2528581e+09 | F7: =VLOOKUP(C7,Hoja2!B:Q,14,0) -> 17016
B8: SURACORTOPLAZOSOLES | C8: SURA CORTO PLAZO SOLES FONDOS SURA SAF | D8: =VLOOKUP("FONDOS SURA SAF-SURA CORTO PLAZO SOLES SERIE A",Hoja2!B:Q,5,0) -> 204.30919 | E8: =VLOOKUP(C8,Hoja2!B:Q,12,0) -> 1.9394846e+08 | F8: =VLOOKUP(C8,Hoja2!B:Q,14,0) -> 874
B9: SURAULTRACASHSOLES | C9: SURA ULTRA CASH SOLES FONDOS SURA SAF | D9: =VLOOKUP("FONDOS SURA SAF-SURA ULTRA CASH SOLES SERIE A",Hoja2!B:Q,5,0) -> 176.48202 | E9: =VLOOKUP(C9,Hoja2!B:Q,12,0) -> 1.6023701e+09 | F9: =VLOOKUP(C9,Hoja2!B:Q,14,0) -> 1979
B10: BBVARENTAMEDPLAZO | C10: BBVA RENTA MED. PLAZO S/. BBVA SAF | D10: =VLOOKUP(C10,Hoja2!B:Q,5,0) -> 411.62103 | E10: =VLOOKUP(C10,Hoja2!B:Q,12,0) -> 4.3828524e+08 | F10: =VLOOKUP(C10,Hoja2!B:Q,14,0) -> 8109
B11: CCMEDPLAZO | C11: CC CONSERV. MED. PLAZO S/. CREDICORP SAF | D11: =VLOOKUP("CREDICORP SAF-CC CONSERV. MED. PLAZO S/. SERIE A",Hoja2!B:Q,5,0) -> 227.19794 | E11: =VLOOKUP(C11,Hoja2!B:Q,12,0) -> 7.5878892e+08 | F11: =VLOOKUP(C11,Hoja2!B:Q,14,0) -> 8001
B12: IFMEDIANOPLAZO | C12: IF MEDIANO PLAZO SOLES INTERFONDO | D12: =VLOOKUP(C12,Hoja2!B:Q,5,0) -> 234.7717 | E12: =VLOOKUP(C12,Hoja2!B:Q,12,0) -> 86245648 | F12: =VLOOKUP(C12,Hoja2!B:Q,14,0) -> 4285
B13: SURARENTASOLES | C13: SURA RENTA SOLES FONDOS SURA SAF | D13: =VLOOKUP("FONDOS SURA SAF-SURA RENTA SOLES SERIE A",Hoja2!B:Q,5,0) -> 243.93946 | E13: =VLOOKUP(C13,Hoja2!B:Q,12,0) -> 1.1773391e+08 | F13: =VLOOKUP(C13,Hoja2!B:Q,14,0) -> 832

Sheet Hoja2
A1: Tipo Fondo | B1: Fondo Mutuo | C1: Administradora | D1: Fec. Inicio Operación | E1: Moneda Cuota | F1: Valor Cuota | G1: Variacion desde el Inicio del 2026 | H1: Rentabilidad(A) 2025 | I1: Rentabilidad(A) 2024 | J1: Rentabilidad(A) 2023 | K1: Rentabilidad(A) 2022 | L1: Rentabilidad(A) 2021 | M1: Patrimonio S/. | N1: Patrimonio % | O1: Partícipes N | P1: Partícipes % | Q1: Inf. Atrasada
A2: 01 - Renta Variable | B2: CREDICORP ACCIONES GLOBAL CREDICORP SAF | C2: CREDICORP SAF | D2: 41358 | E2: $ | F2: 245.42066 | G2: 0.1007 | H2: 0.188 | I2: 0.1326 | J2: 0.1656 | K2: -0.2041 | L2: 0.1397 | M2: 93767260 | N2: 0.0014 | O2: 2452 | P2: 0.0032 | Q2: 46311
A3: 01 - Renta Variable | B3: CREDICORP CAPITAL ACCIONES CREDICORP SAF | C3: CREDICORP SAF | D3: 39099 | E3: $ | F3: 322.37155 | G3: 0.2983 | H3: 0.5002 | I3: 0.0939 | J3: 0.228 | K3: 0.0215 | L3: -0.0644 | M3: 1.4388458e+08 | N3: 0.0022 | O3: 2128 | P3: 0.0028 | Q3: 46311
A4: 01 - Renta Variable | B4: FARO RENTA VARIABLE GLOBAL FARO CAPITAL SAFI | C4: FARO CAPITAL SAFI | D4: 43249 | E4: $ | F4: 0 | M4: 68147270 | N4: 0.001 | O4: 44 | P4: 0.0001 | Q4: 46311
A5: 01 - Renta Variable | B5: FARO CAPITAL SAFI-FARO RENTA VARIABLE GLOBAL SERIE A | C5: FARO CAPITAL SAFI | D5: 43249 | E5: $ | F5: 197.69725 | G5: 0.1161 | H5: 0.1561 | I5: 0.1276 | J5: 0.1724 | K5: -0.206 | L5: 0.1192 | O5: 3 | P5: 0 | Q5: 46311
A6: 01 - Renta Variable | B6: FARO CAPITAL SAFI-FARO RENTA VARIABLE GLOBAL SERIE B | C6: FARO CAPITAL SAFI | D6: 43249 | E6: $ | F6: 193.17448 | G6: 0.114 | H6: 0.1534 | I6: 0.1249 | J6: 0.1697 | K6: -0.208 | L6: 0.1165 | O6: 7 | P6: 0 | Q6: 46311
A7: 01 - Renta Variable | B7: FARO CAPITAL SAFI-FARO RENTA VARIABLE GLOBAL SERIE C | C7: FARO CAPITAL SAFI | D7: 43249 | E7: $ | F7: 186.39765 | G7: 0.1119 | H7: 0.1506 | I7: 0.1198 | J7: 0.1642 | K7: -0.2117 | L7: 0.1113 | O7: 34 | P7: 0 | Q7: 46311
A8: 01 - Renta Variable | B8: IF ACCIONES INTERFONDO | C8: INTERFONDO | D8: 39101 | E8: S/. | F8: 182.3275 | G8: 0.2731 | H8: 0.3395 | I8: 0.0598 | J8: 0.1398 | K8: -0.0743 | L8: 0.075 | M8: 70932353 | N8: 0.0011 | O8: 3815 | P8: 0.005 | Q8: 46311
A9: 01 - Renta Variable | B9: Promoinvest Fondo Selectivo PROMOINVEST SAF | C9: PROMOINVEST SAF | D9: 36174 | E9: $ | F9: 5.6600474 | G9: 0.2166 | H9: 0.4809 | I9: 0.0488 | J9: 0.0595 | K9: -0.0381 | L9: 0.03 | M9: 5493878.7 | N9: 0.0001 | O9: 400 | P9: 0.0005 | Q9: 46311
A10: 01 - Renta Variable | B10: SURA ACCIONES FONDOS SURA SAF | C10: FONDOS SURA SAF | D10: 39104 | E10: S/. | F10: 28.51369 | G10: 0.3342 | H10: 0.3354 | I10: 0.1 | J10: 0.202 | K10: -0.0726 | L10: 0.0576 | M10: 35786896 | N10: 0.0005 | O10: 764 | P10: 0.001 | Q10: 46311
A11: 03 - Renta Mixta Dólares | B11: SF NOTA ESTRUC XVII SCOTIA FONDOS | C11: SCOTIA FONDOS | D11: 46175 | E11: $ | F11: 110.29902 | G11: 0.1021 | M11: 62097949 | N11: 0.0009 | O11: 18 | P11: 0 | Q11: 46311
A12: 06 - Corto Plazo Soles | B12: AC CASH PLUS S/ ANDEAN CROWN SAF S.A.C. | C12: ANDEAN CROWN SAF S.A.C. | D12: 45518 | E12: S/. | F12: 0 | M12: 1230552.2 | N12: 0 | O12: 78 | P12: 0.0001 | Q12: 46311
A13: 06 - Corto Plazo Soles | B13: ANDEAN CROWN SAF S.A.C.-AC CASH PLUS S/ SERIE A | C13: ANDEAN CROWN SAF S.A.C. | D13: 45518 | E13: S/. | F13: 11.290562 | G13: -1 | H13: 0.0547 | I13: 0.0248 | O13: 75 | P13: 0.0001 | Q13: 46295
A14: 06 - Corto Plazo Soles | B14: ANDEAN CROWN SAF S.A.C.-AC CASH PLUS S/ SERIE B | C14: ANDEAN CROWN SAF S.A.C. | D14: 45518 | E14: S/. | F14: 11.096746 | G14: -1 | H14: 0.0573 | O14: 1 | P14: 0 | Q14: 46295
A15: 06 - Corto Plazo Soles | B15: Prudential Corto Plazo S/. PRUDENTIAL SAF | C15: PRUDENTIAL SAF | D15: 45386 | E15: S/. | F15: 0 | M15: 37843810 | N15: 0.0006 | O15: 333 | P15: 0.0004 | Q15: 46311
A16: 06 - Corto Plazo Soles | B16: PRUDENTIAL SAF-Prudential Corto Plazo S/. SERIE A | C16: PRUDENTIAL SAF | D16: 45386 | E16: S/. | F16: 11.505989 | G16: 0.031 | H16: 0.0405 | I16: 0.0343 | O16: 333 | P16: 0.0004 | Q16: 46311
A17: 06 - Corto Plazo Soles | B17: PRUDENTIAL SAF-Prudential Corto Plazo S/. SERIE B | C17: PRUDENTIAL SAF | D17: 45386 | E17: S/. | F17: 11.109104 | G17: -1 | H17: 0.0417 | I17: 0.0349 | O17: 1 | P17: 0 | Q17: 46055
A18: 07 - Corto Plazo Dólares | B18: Andean Crown Cash Plus $ ANDEAN CROWN SAF S.A.C. | C18: ANDEAN CROWN SAF S.A.C. | D18: 45394 | E18: $ | F18: 0 | M18: 1726033.5 | N18: 0 | O18: 93 | P18: 0.0001 | Q18: 46311
A19: 07 - Corto Plazo Dólares | B19: ANDEAN CROWN SAF S.A.C.-Andean Crown Cash Plus $ SERIE A | C19: ANDEAN CROWN SAF S.A.C. | D19: 45394 | E19: $ | F19: 11.269038 | G19: -1 | H19: 0.0515 | I19: 0.0337 | O19: 84 | P19: 0.0001 | Q19: 46295
A20: 07 - Corto Plazo Dólares | B20: ANDEAN CROWN SAF S.A.C.-Andean Crown Cash Plus $ SERIE B | C20: ANDEAN CROWN SAF S.A.C. | D20: 45394 | E20: $ | F20: 10.557894 | G20: -1 | H20: -0.0162 | I20: 0.0351 | O20: 3 | P20: 0 | Q20: 46295
A21: 07 - Corto Plazo Dólares | B21: Prudential Corto Plazo $ PRUDENTIAL SAF | C21: PRUDENTIAL SAF | D21: 45505 | E21: $ | F21: 0 | M21: 32105328 | N21: 0.0005 | O21: 267 | P21: 0.0004 | Q21: 46311
A22: 07 - Corto Plazo Dólares | B22: PRUDENTIAL SAF-Prudential Corto Plazo $ SERIE A | C22: PRUDENTIAL SAF | D22: 45505 | E22: $ | F22: 11.241484 | G22: 0.0249 | H22: 0.0313 | I22: 0.0168 | O22: 267 | P22: 0.0004 | Q22: 46311
A23: 07 - Corto Plazo Dólares | B23: PRUDENTIAL SAF-Prudential Corto Plazo $ SERIE B | C23: PRUDENTIAL SAF | D23: 45505 | E23: $ | F23: 10.881895 | G23: -1 | H23: 0.0325 | I23: 0.0173 | O23: 1 | P23: 0 | Q23: 46030
A24: 12 - Estructurado | B24: CC 24M CUP MEM $ 1 CREDICORP SAF | C24: CREDICORP SAF | D24: 46274 | E24: $ | F24: 101.11711 | G24: 0.0098 | M24: 23333844 | N24: 0.0004 | O24: 116 | P24: 0.0002 | Q24: 46311
A25: 12 - Estructurado | B25: CC 24M CUP MEM $ 2 CREDICORP SAF | C25: CREDICORP SAF | D25: 46309 | E25: $ | F25: 100.20036 | G25: 0.0003 | M25: 15503426 | N25: 0.0002 | O25: 82 | P25: 0.0001 | Q25: 46311
A26: 12 - Estructurado | B26: CC 24M CUP MEM S/ 1 CREDICORP SAF | C26: CREDICORP SAF | D26: 46273 | E26: S/. | F26: 100.3554 | G26: 0.0015 | M26: 11044471 | N26: 0.0002 | O26: 121 | P26: 0.0002 | Q26: 46311
A27: 12 - Estructurado | B27: CC 24M CUP MEM S/ 2 CREDICORP SAF | C27: CREDICORP SAF | D27: 46304 | E27: S/. | F27: 99.059314 | G27: -0.0114 | M27: 10574366 | N27: 0.0002 | O27: 112 | P27: 0.0001 | Q27: 46311
A28: 12 - Estructurado | B28: CC 3M INV GLOB 10 CREDICORP SAF | C28: CREDICORP SAF | D28: 46212 | E28: $ | F28: 100.92503 | G28: -1 | M28: 76349197 | N28: 0.0012 | O28: 225 | P28: 0.0003 | Q28: 46308
A29: 12 - Estructurado | B29: CC 3M INV GLOB 11 CREDICORP SAF | C29: CREDICORP SAF | D29: 46227 | E29: $ | F29: 100.84312 | G29: 0.0075 | M29: 51460357 | N29: 0.0008 | O29: 184 | P29: 0.0002 | Q29: 46311
A30: 12 - Estructurado | B30: CC 3M INV GLOB 12 CREDICORP SAF | C30: CREDICORP SAF | D30: 46247 | E30: $ | F30: 100.63665 | G30: 0.0053 | M30: 48688613 | N30: 0.0007 | O30: 189 | P30: 0.0002 | Q30: 46311
A31: 12 - Estructurado | B31: CC 3M INV GLOB 13 CREDICORP SAF | C31: CREDICORP SAF | D31: 46266 | E31: $ | F31: 100.48948 | G31: 0.0038 | M31: 54547353 | N31: 0.0008 | O31: 176 | P31: 0.0002 | Q31: 46311
A32: 12 - Estructurado | B32: CC 3M INV GLOB 14 CREDICORP SAF | C32: CREDICORP SAF | D32: 46281 | E32: $ | F32: 100.34779 | G32: 0.0025 | M32: 62597551 | N32: 0.001 | O32: 174 | P32: 0.0002 | Q32: 46311
A33: 12 - Estructurado | B33: CC 3M INV GLOB 15 CREDICORP SAF | C33: CREDICORP SAF | D33: 46300 | E33: $ | F33: 100.20022 | G33: 0.001 | M33: 57923219 | N33: 0.0009 | O33: 182 | P33: 0.0002 | Q33: 46311
A34: 12 - Estructurado | B34: CC 3M INV GLOB 8 CREDICORP SAF | C34: CREDICORP SAF | D34: 46177 | E34: $ | F34: 100.94238 | G34: -1 | M34: -0.11 | N34: 0 | O34: 1 | P34: 0 | Q34: 46274
A35: 12 - Estructurado | B35: CC 3M INV GLOB 9 CREDICORP SAF | C35: CREDICORP SAF | D35: 46195 | E35: $ | F35: 100.9394 | G35: -1 | M35: 62394372 | N35: 0.0009 | O35: 190 | P35: 0.0003 | Q35: 46289
... A40: 12 - Estructurado | B40: IF V CAPITAL INTERFONDO | C40: INTERFONDO | D40: 46308 | E40: S/. | F40: 100.1895 | G40: -0.0005 | M40: 32025942 | N40: 0.0005 | O40: 146 | P40: 0.0002 | Q40: 46311
A41: 14 - Renta Mixta Crecimiento Soles | B41: CRED. CRECIMIENTO VCS CREDICORP SAF | C41: CREDICORP SAF | D41: 39618 | E41: S/. | F41: 234.47232 | G41: 0.2019 | H41: 0.2258 | I41: 0.0853 | J41: 0.1561 | K41: -0.007 | L41: 0.0144 | M41: 1.6060067e+08 | N41: 0.0024 | O41: 2843 | P41: 0.0038 | Q41: 46311
A42: 17 - Renta Mixta Balanceado Dólares | B42: CRED. EQUILIBRADO CREDICORP SAF | C42: CREDICORP SAF | D42: 39150 | E42: $ | F42: 195.09674 | G42: 0.1382 | H42: 0.1932 | I42: 0.0567 | J42: 0.1281 | K42: -0.0036 | L42: -0.0317 | M42: 1.0261385e+08 | N42: 0.0016 | O42: 1391 | P42: 0.0018 | Q42: 46311
A43: 17 - Renta Mixta Balanceado Dólares | B43: IF MIXTO BALANCEADO INTERFONDO | C43: INTERFONDO | D43: 35064 | E43: $ | F43: 92.0994 | G43: 0.114 | H43: 0.2197 | I43: 0.0473 | J43: 0.1257 | K43: -0.0022 | L43: -0.0388 | M43: 66582019 | N43: 0.001 | O43: 1467 | P43: 0.0019 | Q43: 46311
A44: 18 - Renta Mixta Moderado Soles | B44: CRED. MODERADO VCS CREDICORP SAF | C44: CREDICORP SAF | D44: 39615 | E44: S/. | F44: 186.10984 | G44: 0.059 | H44: 0.1033 | I44: 0.0611 | J44: 0.0881 | K44: -0.0002 | L44: -0.0247 | M44: 58543404 | N44: 0.0009 | O44: 1344 | P44: 0.0018 | Q44: 46311
A45: 19 - Renta Mixta Moderado Dólares | B45: CRED. MODERADO CREDICORP SAF | C45: CREDICORP SAF | D45: 37513 | E45: $ | F45: 66.090914 | G45: 0.0594 | H45: 0.0972 | I45: 0.0354 | J45: 0.0766 | K45: -0.0166 | L45: -0.0229 | M45: 81825979 | N45: 0.0012 | O45: 846 | P45: 0.0011 | Q45: 46311
A46: 21 - Inst. Deuda Largo Plazo $ | B46: VC BONOS CORP. LATAM COMPASS GROUP SAFI S.A. | C46: COMPASS GROUP SAFI S.A. | D46: 45908 | E46: $ | F46: 0 | M46: 26906749 | N46: 0.0004 | O46: 26 | P46: 0 | Q46: 46311
A47: 21 - Inst. Deuda Largo Plazo $ | B47: COMPASS GROUP SAFI S.A.-VC BONOS CORP. LATAM SERIE A | C47: COMPASS GROUP SAFI S.A. | D47: 45908 | E47: $ | F47: 999.13 | G47: -0.016 | H47: 0.0154 | O47: 19 | P47: 0 | Q47: 46311
A48: 21 - Inst. Deuda Largo Plazo $ | B48: COMPASS GROUP SAFI S.A.-VC BONOS CORP. LATAM SERIE B | C48: COMPASS GROUP SAFI S.A. | D48: 45908 | E48: $ | F48: 973.36 | O48: 3 | P48: 0 | Q48: 46311
A49: 21 - Inst. Deuda Largo Plazo $ | B49: COMPASS GROUP SAFI S.A.-VC BONOS CORP. LATAM SERIE C | C49: COMPASS GROUP SAFI S.A. | D49: 45908 | E49: $ | F49: 996.4 | G49: -0.0168 | O49: 4 | P49: 0 | Q49: 46311
A50: 22 - Inst. Deuda Mediano Plazo S/ | B50: BBVA RENTA MED. PLAZO S/. BBVA SAF | C50: BBVA SAF | D50: 35720 | E50: S/. | F50: 411.62103 | G50: 0.0228 | H50: 0.0785 | I50: 0.0617 | J50: 0.1032 | K50: 0.0056 | L50: -0.0486 | M50: 4.3828524e+08 | N50: 0.0067 | O50: 8109 | P50: 0.0107 | Q50: 46311
A51: 22 - Inst. Deuda Mediano Plazo S/ | B51: CC CONSERV. MED. PLAZO S/. CREDICORP SAF | C51: CREDICORP SAF | D51: 39150 | E51: S/. | F51: 0 | G51: -1 | H51: 0.0673 | I51: 0.0722 | J51: 0.0917 | K51: 0.0023 | L51: -0.0343 | M51: 7.5878892e+08 | N51: 0.0116 | O51: 8001 | P51: 0.0106 | Q51: 46311
A52: 22 - Inst. Deuda Mediano Plazo S/ | B52: CREDICORP SAF-CC CONSERV. MED. PLAZO S/. SERIE A | C52: CREDICORP SAF | D52: 39150 | E52: S/. | F52: 227.19794 | O52: 7905 | P52: 0.0104 | Q52: 46311
A53: 22 - Inst. Deuda Mediano Plazo S/ | B53: CREDICORP SAF-CC CONSERV. MED. PLAZO S/. SERIE B | C53: CREDICORP SAF | D53: 39150 | E53: S/. | F53: 227.19794 | O53: 96 | P53: 0.0001 | Q53: 46311
A54: 22 - Inst. Deuda Mediano Plazo S/ | B54: IF MEDIANO PLAZO SOLES INTERFONDO | C54: INTERFONDO | D54: 37329 | E54: S/. | F54: 234.7717 | G54: 0.015 | H54: 0.0617 | I54: 0.064 | J54: 0.0926 | K54: -0.0675 | L54: -0.0386 | M54: 86245648 | N54: 0.0013 | O54: 4285 | P54: 0.0057 | Q54: 46311
A55: 22 - Inst. Deuda Mediano Plazo S/ | B55: SURA RENTA SOLES FONDOS SURA SAF | C55: FONDOS SURA SAF | D55: 38856 | E55: S/. | F55: 0 | H55: -1 | I55: 0.0633 | J55: 0.0786 | K55: 0.0132 | L55: -0.0256 | M55: 1.1773391e+08 | N55: 0.0018 | O55: 832 | P55: 0.0011 | Q55: 46311
A56: 22 - Inst. Deuda Mediano Plazo S/ | B56: FONDOS SURA SAF-SURA RENTA SOLES SERIE A | C56: FONDOS SURA SAF | D56: 38856 | E56: S/. | F56: 243.93946 | G56: 0.0203 | O56: 8 | P56: 0 | Q56: 46311
A57: 22 - Inst. Deuda Mediano Plazo S/ | B57: FONDOS SURA SAF-SURA RENTA SOLES SERIE B | C57: FONDOS SURA SAF | D57: 38856 | E57: S/. | F57: 105.95628 | G57: 0.0189 | O57: 825 | P57: 0.0011 | Q57: 46311
A58: 23 - Inst. Deuda Mediano Plazo $ | B58: BBVA RENTA MED. PLAZO $ BBVA SAF | C58: BBVA SAF | D58: 35724 | E58: $ | F58: 222.66847 | G58: 0.0067 | H58: 0.0719 | I58: 0.0486 | J58: 0.0607 | K58: -0.0366 | L58: -0.0268 | M58: 5.2173921e+08 | N58: 0.0079 | O58: 3153 | P58: 0.0042 | Q58: 46311
A59: 23 - Inst. Deuda Mediano Plazo $ | B59: IF MEDIANO PLAZO INTERFONDO | C59: INTERFONDO | D59: 35674 | E59: $ | F59: 118.8357 | G59: 0.0003 | H59: 0.0505 | I59: 0.0323 | J59: 0.0331 | K59: -0.0439 | L59: -0.0142 | M59: 87105703 | N59: 0.0013 | O59: 3895 | P59: 0.0051 | Q59: 46311
A60: 24 - Inst. Deuda Corto Plazo S/ | B60: BBVA CASH SOLES BBVA SAF | C60: BBVA SAF | D60: 39784 | E60: S/. | F60: 175.83459 | G60: 0.0315 | H60: 0.0413 | I60: 0.0543 | J60: 0.0713 | K60: 0.038 | L60: 0.001 | M60: 2.7054502e+09 | N60: 0.0412 | O60: 75059 | P60: 0.0992 | Q60: 46311
A61: 24 - Inst. Deuda Corto Plazo S/ | B61: BBVA RENTA CORTO PLAZO S/. BBVA SAF | C61: BBVA SAF | D61: 38713 | E61: S/. | F61: 215.18729 | G61: 0.033 | H61: 0.0517 | I61: 0.0561 | J61: 0.0768 | K61: 0.0272 | L61: -0.0195 | M61: 9.0160384e+08 | N61: 0.0137 | O61: 7051 | P61: 0.0093 | Q61: 46311
A62: 24 - Inst. Deuda Corto Plazo S/ | B62: BBVA TESORERIA SOLES FMIV BBVA SAF | C62: BBVA SAF | D62: 43376 | E62: S/. | F62: 136.05661 | G62: 0.0331 | H62: 0.0427 | I62: 0.0557 | J62: 0.0708 | K62: 0.0344 | L62: 0.0014 | M62: 3.9166551e+08 | N62: 0.006 | O62: 614 | P62: 0.0008 | Q62: 46311
A63: 24 - Inst. Deuda Corto Plazo S/ | B63: CRED. CONSER. CORTO PLAZO S/ CREDICORP SAF | C63: CREDICORP SAF | D63: 41680 | E63: S/. | F63: 0 | G63: -1 | H63: 0.047 | I63: 0.0602 | J63: 0.0754 | K63: 0.0329 | L63: -0.0076 | M63: 1.3128841e+09 | N63: 0.02 | O63: 13772 | P63: 0.0182 | Q63: 46311
A64: 24 - Inst. Deuda Corto Plazo S/ | B64: CREDICORP SAF-CRED. CONSER. CORTO PLAZO S/ SERIE A | C64: CREDICORP SAF | D64: 41680 | E64: S/. | F64: 166.77473 | O64: 13610 | P64: 0.018 | Q64: 46311
A65: 24 - Inst. Deuda Corto Plazo S/ | B65: CREDICORP SAF-CRED. CONSER. CORTO PLAZO S/ SERIE B | C65: CREDICORP SAF | D65: 41680 | E65: S/. | F65: 166.77473 | O65: 162 | P65: 0.0002 | Q65: 46311
A66: 24 - Inst. Deuda Corto Plazo S/ | B66: CRED. CONSERVAD. LIQUIDEZ S/ CREDICORP SAF | C66: CREDICORP SAF | D66: 36622 | E66: S/. | F66: 0 | G66: -1 | H66: 0.0428 | I66: 0.0549 | J66: 0.0721 | K66: 0.0457 | L66: 0.002 | M66: 3.4812322e+09 | N66: 0.053 | O66: 45788 | P66: 0.0605 | Q66: 46311
A67: 24 - Inst. Deuda Corto Plazo S/ | B67: CREDICORP SAF-CRED. CONSERVAD. LIQUIDEZ S/ SERIE A | C67: CREDICORP SAF | D67: 36622 | E67: S/. | F67: 361.75433 | O67: 45110 | P67: 0.0596 | Q67: 46311
A68: 24 - Inst. Deuda Corto Plazo S/ | B68: CREDICORP SAF-CRED. CONSERVAD. LIQUIDEZ S/ SERIE B | C68: CREDICORP SAF | D68: 36622 | E68: S/. | F68: 361.76927 | O68: 678 | P68: 0.0009 | Q68: 46311
A69: 24 - Inst. Deuda Corto Plazo S/ | B69: DIVISO CONSERVADOR SOLES | D69: 41486 | E69: S/. | F69: 14.69556 | G69: -1 | H69: -0.8989 | I69: -0.0384 | J69: 0.077 | K69: 0.0495 | L69: 0.0145 | M69: 140451.11 | N69: 0 | O69: 117 | P69: 0.0002 | Q69: 46132
A70: 24 - Inst. Deuda Corto Plazo S/ | B70: SF Liquidez S/. SCOTIA FONDOS | C70: SCOTIA FONDOS | D70: 44956 | E70: S/. | F70: 12.225661 | G70: 0.0327 | H70: 0.0426 | I70: 0.0503 | J70: 0.0635 | M70: 1.2528581e+09 | N70: 0.0191 | O70: 17016 | P70: 0.0225 | Q70: 46311
A71: 24 - Inst. Deuda Corto Plazo S/ | B71: SURA CORTO PLAZO SOLES FONDOS SURA SAF | C71: FONDOS SURA SAF | D71: 39897 | E71: S/. | F71: 0 | H71: -1 | I71: 0.0598 | J71: 0.067 | K71: 0.0394 | L71: -0.0067 | M71: 1.9394846e+08 | N71: 0.003 | O71: 874 | P71: 0.0012 | Q71: 46311
A72: 24 - Inst. Deuda Corto Plazo S/ | B72: FONDOS SURA SAF-SURA CORTO PLAZO SOLES SERIE A | C72: FONDOS SURA SAF | D72: 39897 | E72: S/. | F72: 204.30919 | G72: 0.0289 | O72: 51 | P72: 0.0001 | Q72: 46311
A73: 24 - Inst. Deuda Corto Plazo S/ | B73: FONDOS SURA SAF-SURA CORTO PLAZO SOLES SERIE B | C73: FONDOS SURA SAF | D73: 39897 | E73: S/. | F73: 105.48772 | G73: 0.0279 | O73: 824 | P73: 0.0011 | Q73: 46311
A74: 24 - Inst. Deuda Corto Plazo S/ | B74: SURA ULTRA CASH SOLES FONDOS SURA SAF | C74: FONDOS SURA SAF | D74: 41038 | E74: S/. | F74: 0 | H74: -1 | I74: 0.0558 | J74: 0.0732 | K74: 0.0462 | L74: 0.0052 | M74: 1.6023701e+09 | N74: 0.0244 | O74: 1979 | P74: 0.0026 | Q74: 46311
A75: 24 - Inst. Deuda Corto Plazo S/ | B75: FONDOS SURA SAF-SURA ULTRA CASH SOLES SERIE A | C75: FONDOS SURA SAF | D75: 41038 | E75: S/. | F75: 176.48202 | G75: 0.0334 | O75: 272 | P75: 0.0004 | Q75: 46311
A76: 24 - Inst. Deuda Corto Plazo S/ | B76: FONDOS SURA SAF-SURA ULTRA CASH SOLES SERIE B | C76: FONDOS SURA SAF | D76: 41038 | E76: S/. | F76: 105.79282 | G76: 0.0315 | O76: 1709 | P76: 0.0023 | Q76: 46311
A77: 25 - Inst. Deuda Corto Plazo $ | B77: BBVA CASH DOLARES BBVA SAF | C77: BBVA SAF | D77: 39784 | E77: $ | F77: 130.88187 | G77: 0.0278 | H77: 0.0389 | I77: 0.048 | J77: 0.0442 | K77: 0.0122 | L77: 0.001 | M77: 4.888928e+09 | N77: 0.0744 | O77: 25725 | P77: 0.034 | Q77: 46311
A78: 25 - Inst. Deuda Corto Plazo $ | B78: BBVA RENTA CORTO PLAZO $ BBVA SAF | C78: BBVA SAF | D78: 36693 | E78: $ | F78: 193.02563 | G78: 0.0236 | H78: 0.0489 | I78: 0.0522 | J78: 0.0465 | K78: 0.0036 | L78: 0.0021 | M78: 2.5100021e+09 | N78: 0.0382 | O78: 6150 | P78: 0.0081 | Q78: 46311
A79: 25 - Inst. Deuda Corto Plazo $ | B79: CRED. CONSER. CORTO PLAZO $ CREDICORP SAF | C79: CREDICORP SAF | D79: 41688 | E79: $ | F79: 0 | G79: -1 | H79: 0.0467 | I79: 0.0534 | J79: 0.0516 | K79: 0.0145 | L79: 0.0034 | M79: 3.4635061e+09 | N79: 0.0527 | O79: 10884 | P79: 0.0144 | Q79: 46311
A80: 25 - Inst. Deuda Corto Plazo $ | B80: CREDICORP SAF-CRED. CONSER. CORTO PLAZO $ SERIE A | C80: CREDICORP SAF | D80: 41688 | E80: $ | F80: 134.55519 | O80: 10671 | P80: 0.0141 | Q80: 46311
A81: 25 - Inst. Deuda Corto Plazo $ | B81: CREDICORP SAF-CRED. CONSER. CORTO PLAZO $ SERIE B | C81: CREDICORP SAF | D81: 41688 | E81: $ | F81: 134.56088 | O81: 213 | P81: 0.0003 | Q81: 46311
A82: 25 - Inst. Deuda Corto Plazo $ | B82: CRED. CONSERVADOR LIQUIDEZ $ CREDICORP SAF | C82: CREDICORP SAF | D82: 36286 | E82: $ | F82: 0 | G82: -1 | H82: 0.0383 | I82: 0.0493 | J82: 0.0483 | K82: 0.0158 | L82: 0.0028 | M82: 6.5987617e+09 | N82: 0.1005 | O82: 28003 | P82: 0.037 | Q82: 46311
A83: 25 - Inst. Deuda Corto Plazo $ | B83: CREDICORP SAF-CRED. CONSERVADOR LIQUIDEZ $ SERIE A | C83: CREDICORP SAF | D83: 36286 | E83: $ | F83: 201.4223 | O83: 27344 | P83: 0.0361 | Q83: 46311
A84: 25 - Inst. Deuda Corto Plazo $ | B84: CREDICORP SAF-CRED. CONSERVADOR LIQUIDEZ $ SERIE B | C84: CREDICORP SAF | D84: 36286 | E84: $ | F84: 201.42913 | O84: 659 | P84: 0.0009 | Q84: 46311
A85: 25 - Inst. Deuda Corto Plazo $ | B85: DIVISO CONSERVADOR DOLARES | D85: 42082 | E85: $ | F85: 56.964768 | G85: -1 | H85: -0.4929 | I85: -0.0777 | J85: 0.0536 | K85: 0.0088 | L85: 0.0293 | M85: 309519.3 | N85: 0 | O85: 38 | P85: 0.0001 | Q85: 46132
A86: 25 - Inst. Deuda Corto Plazo $ | B86: FARO CORTO PLAZO DOLARES FARO CAPITAL SAFI | C86: FARO CAPITAL SAFI | D86: 44782 | E86: $ | F86: 0 | M86: 11984827 | N86: 0.0002 | O86: 35 | P86: 0 | Q86: 46311
A87: 25 - Inst. Deuda Corto Plazo $ | B87: FARO CAPITAL SAFI-FARO CORTO PLAZO DOLARES SERIE A | C87: FARO CAPITAL SAFI | D87: 44782 | E87: $ | F87: 104.67984 | G87: 0.0272 | H87: -0.0448 | I87: 0.047 | J87: 0.0089 | K87: 0.0094 | O87: 2 | P87: 0 | Q87: 46311
A88: 25 - Inst. Deuda Corto Plazo $ | B88: FARO CAPITAL SAFI-FARO CORTO PLAZO DOLARES SERIE B | C88: FARO CAPITAL SAFI | D88: 44782 | E88: $ | F88: 117.86008 | G88: 0.0268 | H88: 0.0377 | I88: 0.046 | J88: 0.0448 | K88: 0.0092 | O88: 33 | P88: 0 | Q88: 46311
A89: 25 - Inst. Deuda Corto Plazo $ | B89: SF LIQUIDEZ $ SCOTIA FONDOS | C89: SCOTIA FONDOS | D89: 44957 | E89: $ | F89: 11.688512 | G89: 0.0268 | H89: 0.0383 | I89: 0.0461 | J89: 0.0422 | M89: 3.3474209e+09 | N89: 0.051 | O89: 14223 | P89: 0.0188 | Q89: 46311
A90: 25 - Inst. Deuda Corto Plazo $ | B90: SURA CORTO PLAZO DOLARES FONDOS SURA SAF | C90: FONDOS SURA SAF | D90: 40056 | E90: $ | F90: 0 | H90: -1 | I90: 0.0486 | J90: 0.0482 | K90: 0.0138 | L90: 0.0065 | M90: 3.7221032e+08 | N90: 0.0057 | O90: 1230 | P90: 0.0016 | Q90: 46311
A91: 25 - Inst. Deuda Corto Plazo $ | B91: FONDOS SURA SAF-SURA CORTO PLAZO DOLARES SERIE A | C91: FONDOS SURA SAF | D91: 40056 | E91: $ | F91: 147.81463 | G91: 0.0241 | O91: 56 | P91: 0.0001 | Q91: 46311
A92: 25 - Inst. Deuda Corto Plazo $ | B92: FONDOS SURA SAF-SURA CORTO PLAZO DOLARES SERIE B | C92: FONDOS SURA SAF | D92: 40056 | E92: $ | F92: 104.99386 | G92: 0.0222 | O92: 1175 | P92: 0.0016 | Q92: 46311
A93: 25 - Inst. Deuda Corto Plazo $ | B93: SURA ULTRA CASH DOLARES FONDOS SURA SAF | C93: FONDOS SURA SAF | D93: 41109 | E93: $ | F93: 0 | H93: -1 | I93: 0.0487 | J93: 0.0479 | K93: 0.0149 | L93: 0.0041 | M93: 1.3248798e+09 | N93: 0.0202 | O93: 1692 | P93: 0.0022 | Q93: 46311
A94: 25 - Inst. Deuda Corto Plazo $ | B94: FONDOS SURA SAF-SURA ULTRA CASH DOLARES SERIE A | C94: FONDOS SURA SAF | D94: 41109 | E94: $ | F94: 132.89154 | G94: 0.0277 | O94: 232 | P94: 0.0003 | Q94: 46311
A95: 25 - Inst. Deuda Corto Plazo $ | B95: FONDOS SURA SAF-SURA ULTRA CASH DOLARES SERIE B | C95: FONDOS SURA SAF | D95: 41109 | E95: $ | F95: 104.95127 | G95: 0.0257 | O95: 1461 | P95: 0.0019 | Q95: 46311
A96: 29 - Flexible | B96: BLUM ACC GLOB INST BLUM SAF | C96: BLUM SAF | D96: 46295 | E96: $ | F96: 9.945643 | G96: -0.0054 | M96: 5568839.3 | N96: 0.0001 | O96: 11 | P96: 0 | Q96: 46311
A97: 29 - Flexible | B97: BLUM BONOS GLOBALES FM BLUM SAF | C97: BLUM SAF | D97: 45376 | E97: $ | F97: 11.71547 | G97: 0.0289 | H97: 0.0758 | I97: 0.0559 | M97: 1.8447078e+08 | N97: 0.0028 | O97: 39 | P97: 0.0001 | Q97: 46311
A98: 29 - Flexible | B98: Blum Cash S/ FM BLUM SAF | C98: BLUM SAF | D98: 45272 | E98: S/. | F98: 0 | H98: -1 | I98: 0.0503 | J98: 0.0039 | M98: 8942133.5 | N98: 0.0001 | O98: 7380 | P98: 0.0098 | Q98: 46311
A99: 29 - Flexible | B99: BLUM SAF-Blum Cash S/ FM SERIE A | C99: BLUM SAF | D99: 45272 | E99: S/. | F99: 11.074343 | G99: 0.0281 | O99: 4037 | P99: 0.0053 | Q99: 46311
A100: 29 - Flexible | B100: BLUM SAF-Blum Cash S/ FM SERIE O | C100: BLUM SAF | D100: 45272 | E100: S/. | F100: 12.011117 | G100: 0.0322 | O100: 3361 | P100: 0.0044 | Q100: 46311
A101: 29 - Flexible | B101: BLUM DEUDA PRIV GLOBAL BLUM SAF | C101: BLUM SAF | D101: 45945 | E101: $ | F101: 0 | M101: 6499257.3 | N101: 0.0001 | O101: 21 | P101: 0 | Q101: 46311
A102: 29 - Flexible | B102: BLUM SAF-BLUM DEUDA PRIV GLOBAL SERIE A | C102: BLUM SAF | D102: 45945 | E102: $ | F102: 9.3950902 | G102: -0.083 | O102: 4 | P102: 0 | Q102: 46311
A103: 29 - Flexible | B103: BLUM SAF-BLUM DEUDA PRIV GLOBAL SERIE B | C103: BLUM SAF | D103: 45945 | E103: $ | F103: 9.0982657 | G103: -0.0847 | O103: 17 | P103: 0 | Q103: 46311
A104: 29 - Flexible | B104: BLUM SAF-BLUM DEUDA PRIV GLOBAL SERIE I | C104: BLUM SAF | D104: 45945 | E104: $ | F104: 9.144429 | G104: -0.0812 | O104: 1 | P104: 0 | Q104: 46311
...

Sheet Hoja3
A3: Etiquetas de fila | B3: Suma de Valor Cuota | C3: Suma de Patrimonio
A4: 45946 | B4: 2582.0335 | C4: 1.2558532e+10
A5: BBVACASH | B5: 169.08254 | C5: 2.9146272e+09
A6: BBVARENTACORTOPLAZO | B6: 206.54573 | C6: 9.7219631e+08
A7: BBVARENTAMEDPLAZO | B7: 397.37436 | C7: 3.871654e+08
A8: BBVATESORERIASOLES | B8: 130.56816 | C8: 2.9678436e+08
A9: CCMEDPLAZO | B9: 219.21646 | C9: 7.2364165e+08
A10: CREDCONSERCORTOPLAZO | B10: 160.52852 | C10: 1.212088e+09
A11: CREDCONSERVADLIQUIDEZ | B11: 347.98733 | C11: 2.6510067e+09
A12: ETFPESOV | B12: 107.5995 | C12: 163282307
A13: IFMEDIANOPLAZO | B13: 229.0359 | C13: 1.0284353e+08
A14: SFLiquidez | B14: 11.73933 | C14: 1.1914545e+09
A15: SURACORTOPLAZOSOLES | B15: 196.89077 | C15: 3.1836214e+08
A16: SURARENTASOLES | B16: 236.175 | C16: 1.246272e+08
A17: SURAULTRACASHSOLES | B17: 169.28993 | C17: 1.5004529e+09
A18: 46311 | B18: 2677.1308 | C18: 1.3392643e+10
A19: BBVACASH | B19: 175.83459 | C19: 2.7054502e+09
A20: BBVARENTACORTOPLAZO | B20: 215.18729 | C20: 9.0160384e+08 | E20: Muy Corto Plazo | G20: =SUMPRODUCT(F21:F24,G21:G24)/SUM(G21:G24) -> 204.05176 | L20: =SUMPRODUCT(K21:K24,L21:L24)/SUM(L21:L24) -> 223.96817 | M20: =SUMPRODUCT(M21:M24,L21:L24)/SUM(L21:L24) -> 0.04033333
A21: BBVARENTAMEDPLAZO | B21: 411.62103 | C21: 4.3828524e+08 | E21: CREDCONSERVADLIQUIDEZ | F21: 347.74868 | G21: 2.6958358e+09 | J21: CREDCONSERVADLIQUIDEZ | K21: 361.46005 | L21: 3.4518694e+09 | M21: =K21/F21-1 -> 0.039428964
A22: BBVATESORERIASOLES | B22: 136.05661 | C22: 3.9166551e+08 | E22: SFLiquidez | F22: 11.731006 | G22: 1196654662 | J22: SFLiquidez | K22: 12.215236 | L22: 1.2494352e+09 | M22: =K22/F22-1 -> 0.041277782
A23: CCMEDPLAZO | B23: 227.19794 | C23: 7.5878892e+08 | E23: BBVACASH | F23: 168.95559 | G23: 2.9286036e+09 | J23: BBVACASH | K23: 175.68375 | L23: 2.7057482e+09 | M23: =K23/F23-1 -> 0.039822107
A24: CREDCONSERCORTOPLAZO | B24: 166.77473 | C24: 1.3128841e+09 | E24: SURAULTRACASHSOLES | F24: 169.17041 | G24: 1.5612636e+09 | J24: SURAULTRACASHSOLES | K24: 176.33114 | L24: 1.6664965e+09 | M24: =K24/F24-1 -> 0.042328512
A25: CREDCONSERVADLIQUIDEZ | B25: 361.75433 | C25: 3.4812322e+09
A26: ETFPESOV | B26: 110.9762 | C26: 1.4957643e+08 | E26: Corto Plazo | G26: =SUMPRODUCT(F27:F30,G27:G30)/SUM(G27:G30) -> 177.42128 | L26: =SUMPRODUCT(K27:K30,L27:L30)/SUM(L27:L30) -> 180.36735 | M26: =SUMPRODUCT(M27:M30,L27:L30)/SUM(L27:L30) -> 0.038881799
A27: IFMEDIANOPLAZO | B27: 234.7717 | C27: 86245648 | E27: BBVARENTACORTOPLAZO | F27: 206.46415 | G27: 9.6458152e+08 | J27: BBVARENTACORTOPLAZO | K27: 214.81612 | L27: 8.9701957e+08 | M27: =K27/F27-1 -> 0.040452367
A28: SFLiquidez | B28: 12.225661 | C28: 1.2528581e+09 | E28: BBVATESORERIASOLES | F28: 130.46581 | G28: 2.9310617e+08 | J28: BBVATESORERIASOLES | K28: 135.93526 | L28: 3.8546594e+08 | M28: =K28/F28-1 -> 0.041922488
A29: SURACORTOPLAZOSOLES | B29: 204.30919 | C29: 1.9394846e+08 | E29: CREDCONSERCORTOPLAZO | F29: 160.45289 | G29: 1.2101422e+09 | J29: CREDCONSERCORTOPLAZO | K29: 166.41806 | L29: 1.3177931e+09 | M29: =K29/F29-1 -> 0.037177071
A30: SURARENTASOLES | B30: 243.93946 | C30: 1.1773391e+08 | E30: SURACORTOPLAZOSOLES | F30: 196.71769 | G30: 3.2559922e+08 | J30: SURACORTOPLAZOSOLES | K30: 204.02862 | L30: 1.9475346e+08 | M30: =K30/F30-1 -> 0.037164575
A31: SURAULTRACASHSOLES | B31: 176.48202 | C31: 1.6023701e+09
A32: Total general | B32: 5259.1643 | C32: 2.5951175e+10
N33: =M26*(1-30%) -> 0.027217259
A39: BBVACASH | B39: 169.08254 | C39: 175.83459 | D39: =C39/B39-1 -> 0.039933468 | E39: 2.7054502e+09
A40: BBVARENTACORTOPLAZO | B40: 206.54573 | C40: 215.18729 | D40: =C40/B40-1 -> 0.041838501 | E40: 9.0160384e+08
A41: BBVARENTAMEDPLAZO | B41: 397.37436 | C41: 411.62103 | D41: =C41/B41-1 -> 0.035852013 | E41: 4.3828524e+08
A42: BBVATESORERIASOLES | B42: 130.56816 | C42: 136.05661 | D42: =C42/B42-1 -> 0.042035112 | E42: 3.9166551e+08
A43: CCMEDPLAZO | B43: 219.21646 | C43: 227.19794 | D43: =C43/B43-1 -> 0.036409134 | E43: 7.5878892e+08
A44: CREDCONSERCORTOPLAZO | B44: 160.52852 | C44: 166.77473 | D44: =C44/B44-1 -> 0.038910273 | E44: 1.3128841e+09
A45: CREDCONSERVADLIQUIDEZ | B45: 347.98733 | C45: 361.75433 | D45: =C45/B45-1 -> 0.039561758 | E45: 3.4812322e+09
A46: ETFPESOV | B46: 107.5995 | C46: 110.9762 | D46: =C46/B46-1 -> 0.031382116 | E46: 1.4957643e+08
A47: IFMEDIANOPLAZO | B47: 229.0359 | C47: 234.7717 | D47: =C47/B47-1 -> 0.025043236 | E47: 86245648
A48: SFLiquidez | B48: 11.73933 | C48: 12.225661 | D48: =C48/B48-1 -> 0.04142748 | E48: 1.2528581e+09
A49: SURACORTOPLAZOSOLES | B49: 196.89077 | C49: 204.30919 | D49: =C49/B49-1 -> 0.03767789 | E49: 1.9394846e+08
A50: SURARENTASOLES | B50: 236.175 | C50: 243.93946 | D50: =C50/B50-1 -> 0.032875896 | E50: 1.1773391e+08
A51: SURAULTRACASHSOLES | B51: 169.28993 | C51: 176.48202 | D51: =C51/B51-1 -> 0.042483862 | E51: 1.6023701e+09
A55: CRED. CONSERVAD. LIQUIDEZ S/ CREDICORP SAF | B55: 0.039561758 | C55: 3.4812322e+09 | E55: =SUMPRODUCT(B55:B58,C55:C58)/SUM(C55:C58) -> 0.040449338 | F55: =E55*(1-30%) -> 0.028314537
A56: SF Liquidez S/. SCOTIA FONDOS | B56: 0.04142748 | C56: 1.2528581e+09
A57: BBVA CASH SOLES BBVA SAF | B57: 0.039933468 | C57: 2.7054502e+09
A58: SURA ULTRA CASH SOLES FONDOS SURA SAF​ | B58: 0.042483862 | C58: 1.6023701e+09
A60: BBVA RENTA CORTO PLAZO S/. BBVA SA | B60: 0.041838501 | C60: 9.0160384e+08 | E60: =SUMPRODUCT(B60:B63,C60:C63)/SUM(C60:C63) -> 0.04020486 | F60: =E60*(1-30%) -> 0.028143402
A61: CRED. CONSER. CORTO PLAZO S/ CREDICORP SAF | B61: 0.038910273 | C61: 1.3128841e+09
A62: BBVA TESORERIA SOLES FMIV BBVA SAF | B62: 0.042035112 | C62: 3.9166551e+08
A63: SURA CORTO PLAZO SOLES FONDOS SURA SAF​ | B63: 0.03767789 | C63: 1.9394846e+08
